starlette_logger/__init__.py
starlette_logger/middleware.py
starlette_logger-0.0.5.dist-info/WHEEL
starlette_logger-0.0.5.dist-info/METADATA
starlette_logger-0.0.5.dist-info/RECORD
